[{
	"coords": "[26.07910361, 44.49173717]",
	"culoare": 2,
	"raza": 7,
	"categorie": 1.1,
	"name": "Lucrari de scurta durata  DN1",
	"Judet": "B;",
	"UAT": "București Sectorul 1;",
	"Localitati": "BUCURESTI (B) -",
	"Km": "7+260 - 7+354",
	"Cauza": "Incepand de maine, 14.10.2025, ora 23:00, se vor institui restrictii de circulatie pe DN1, pe sectorul cuprins intre km 7+260 - km 7+354, sensul de deplasare Bucuresti - Ploiesti (inainte de intrarea in pasajul subteran Baneasa).\nAstfel, se va inchide banda 1 de pe acest sector, iar traficul ruti...\n<cite>*Pentru descrierea completa consultati sectiunea drumuri.</cite>",
	"Masuri de remediere": "Trficul se desfasoara pe banda 2 si pe banda 3.",
	"lat": 26.07910361,
	"long": 44.49173717,
	"date_start": "14-10-2025 23:00",
	"date_end": "30-10-2025 23:00",
	"km_start": "7+260",
	"km_end": "7+354"
},
{
	"coords": "[26.21853435, 45.51272922]",
	"culoare": 2,
	"raza": 7,
	"categorie": 6.0,
	"name": "Lucrari  DN10",
	"Judet": "BZ;",
	"UAT": "Siriu;",
	"Localitati": "SIRIU (BZ) - SIRIU (BZ)",
	"Km": "87+000 - 87+088",
	"Tip Lucrari": "Punerea in siguranta drum national DN 10, pentru diminuarea riscului de blocarea acestuia ca urmare a caderii stancilor de pe versant (Aviz restrictie circulatie nr: DRDP: 5580/27.02.2025)",
	"Variante de ocolire": "Circulatie alternanta dirijata cu semafoare si piloti de lucrari pe maxim 1/2 din cale. In intervalul orar 08:00 -18:00, de luni pana vineri, executantul lucrarilor este obligat sa asigure dirijarea circulatiei cu piloti de circulatie, ce vor fi dotati cu palete de semnalizare cu fete duble (rosu-ve...\n<cite>*Pentru descrierea completa consultati sectiunea drumuri.</cite>",
	"lat": 26.21853435,
	"long": 45.51272922,
	"date_start": "06-03-2025 08:00",
	"date_end": "15-12-2025 18:00",
	"km_start": "87+000",
	"km_end": "87+088"
},
{
	"coords": "[27.31875543, 46.19515252]",
	"culoare": 0,
	"raza": 7,
	"categorie": 5.0,
	"name": "Circulatie ingreunata  DN11A",
	"Judet": "VN;",
	"UAT": "Corbița;",
	"Localitati": "LEHANCEA (BC) - LEHANCEA (BC)",
	"Km": "59+455 - 59+535",
	"Cauza": "Ravenari terasament corp drum.",
	"Masuri de remediere": "Latime - 5m. Viteza - 40km/h",
	"lat": 27.31875543,
	"long": 46.19515252,
	"date_start": "08-11-2024 09:31",
	"date_end": "31-12-2025 23:59",
	"km_start": "59+455",
	"km_end": "59+535"
},
{
	"coords": "[27.32955675, 46.19365334]",
	"culoare": 0,
	"raza": 7,
	"categorie": 5.0,
	"name": "Circulatie ingreunata  DN11A",
	"Judet": "BC;",
	"UAT": "Podu Turcului;",
	"Localitati": "LEHANCEA (BC) - LEHANCEA (BC)",
	"Km": "60+225 - 60+305",
	"Cauza": "Ravenari terasament corp drum.",
	"Masuri de remediere": "Latime - 3m. Viteza - 40km/h.",
	"lat": 27.32955675,
	"long": 46.19365334,
	"date_start": "08-11-2024 09:36",
	"date_end": "31-12-2025 23:59",
	"km_start": "60+225",
	"km_end": "60+305"
},
{
	"coords": "[26.82217697, 46.5329543]",
	"culoare": 2,
	"raza": 7,
	"categorie": 6.0,
	"name": "Lucrari  DN11",
	"Judet": "BC;",
	"UAT": "Luizi-Călugăra;",
	"Localitati": "BARZULESTI (BC) - BARZULESTI (BC)",
	"Km": "167+010 - 167+086",
	"Tip Lucrari": "Consolidarea acostamentului in urma unor alunecari aparute pe fondul ploilor abundente.",
	"Variante de ocolire": "Se circula semaforizat pe un singur sens.",
	"lat": 26.82217697,
	"long": 46.5329543,
	"date_start": "29-05-2025 00:00",
	"date_end": "31-10-2025 11:00",
	"km_start": "167+010",
	"km_end": "167+086"
},
{
	"coords": "[24.45856695, 45.05192312]",
	"culoare": 0,
	"raza": 7,
	"categorie": 5.0,
	"name": "Circulatie ingreunata  DN7",
	"Judet": "VL;",
	"UAT": "Golești;",
	"Localitati": "MILCOIU (VL) -",
	"Km": "162+390 - 162+460",
	"Cauza": "Alunecare de teren activa.",
	"Masuri de remediere": "Circulatia rutiera se desfasoara pe ambele sensuri de mers , cu precizarea ca pe sensul Rm. Valcea - Pitesti circulatia se desfasoara pe o singura banda din doua. Au fost montate indicatoare rutiere de restrictii de circulatie conform schemei de semnalizare C1.",
	"lat": 24.45856695,
	"long": 45.05192312,
	"date_start": "01-06-2025 00:00",
	"date_end": "01-12-2025 16:00",
	"km_start": "162+390",
	"km_end": "162+460"
},
{
	"coords": "[26.21800041, 45.51350021]",
	"culoare": 2,
	"raza": 7,
	"categorie": 6.0,
	"name": "Lucrari  DN10",
	"Judet": "BZ;",
	"UAT": "Siriu;",
	"Localitati": "SIRIU (BZ) - SIRIU (BZ)",
	"Km": "87+106 - 87+172",
	"Tip Lucrari": "Punerea in siguranta drum national DN 10, pentru diminuarea riscului de blocarea acestuia ca urmare a caderii stancilor de pe versant (Aviz restrictie circulatie nr: DRDP: 5580/27.02.2025)",
	"Variante de ocolire": "Circulatie alternanta dirijata cu semafoare si piloti de lucrari pe maxim 1/2 din cale. In intervalul orar 08:00 -18:00, de luni pana vineri, executantul lucrarilor este obligat sa asigure dirijarea circulatiei cu piloti de circulatie, ce vor fi dotati cu palete de semnalizare cu fete duble (rosu-ve...\n<cite>*Pentru descrierea completa consultati sectiunea drumuri.</cite>",
	"lat": 26.21800041,
	"long": 45.51350021,
	"date_start": "06-03-2025 08:00",
	"date_end": "15-12-2025 18:00",
	"km_start": "87+106",
	"km_end": "87+172"
},
{
	"coords": "[23.87478675, 47.15470186]",
	"culoare": 2,
	"raza": 7,
	"categorie": 6.0,
	"name": "Lucrari  DN1C",
	"Judet": "CJ;",
	"UAT": "Dej;",
	"Localitati": "DEJ (CJ) - DEJ (CJ)",
	"Km": "61+451 - 61+513",
	"Tip Lucrari": "Lucrari de reabilitare pod.",
	"Variante de ocolire": "Circulatia se desfasoara alternativ pe o singura banda.",
	"lat": 23.87478675,
	"long": 47.15470186,
	"date_start": "06-10-2025 08:00",
	"date_end": "26-10-2025 18:00",
	"km_start": "61+451",
	"km_end": "61+513"
},
{
	"coords": "[26.73149618, 45.58593618]",
	"culoare": 0,
	"raza": 7,
	"categorie": 5.0,
	"name": "Circulatie ingreunata  DN2R",
	"Judet": "VN;",
	"UAT": "Jitia;",
	"Localitati": "VINTILEASCA (VN) - VINTILEASCA (VN)",
	"Km": "1+860 - 1+920",
	"Cauza": "Alunecare teren, tasare platforma drum.",
	"Masuri de remediere": "Latime - 2,5m.",
	"lat": 26.73149618,
	"long": 45.58593618,
	"date_start": "08-11-2024 09:44",
	"date_end": "31-12-2025 23:59",
	"km_start": "1+860",
	"km_end": "1+920"
},
{
	"coords": "[26.76642969, 45.58101992]",
	"culoare": 0,
	"raza": 7,
	"categorie": 5.0,
	"name": "Circulatie ingreunata  DN2N",
	"Judet": "VN;",
	"UAT": "Jitia;",
	"Localitati": "JITIA (VN) - JITIA (VN)",
	"Km": "50+400 - 50+460",
	"Cauza": "Reactivare alunecare teren.",
	"Masuri de remediere": "Circulatie ingreunata.",
	"lat": 26.76642969,
	"long": 45.58101992,
	"date_start": "08-11-2024 09:54",
	"date_end": "31-12-2025 23:59",
	"km_start": "50+400",
	"km_end": "50+460"
},
{
	"coords": "[24.29223421, 45.47571313]",
	"culoare": 0,
	"raza": 7,
	"categorie": 5.0,
	"name": "Circulatie ingreunata  DN7",
	"Judet": "VL;",
	"UAT": "Cîineni;",
	"Localitati": "CAINENII MARI (VL) -",
	"Km": "228+850 - 228+900",
	"Cauza": "Datorita caderilor de pietre pentru siguranta participantilor la trafic pe sectorul de drum mai sus mentionat au fost instalate masuri de semnalizare corespunzatoare conform schemei de semnalizare B1. Circulatia se desfasoara ingreunat.",
	"Masuri de remediere": "Latimea benzii de circulatie pe sensul de mers Rm. Valcea - Sibiu este de 3,73 m , iar latimea benzi de circulatie pe sensul de mers Sibiu - Rm. Valcea este de 3,25.\nCirculatia rutiera se desfasoara normal pe sensul Rm. Valcea - Sibiu (avand latimea benzii de 3,75m) , si ingreunat pe sensul Sibiu...\n<cite>*Pentru descrierea completa consultati sectiunea drumuri.</cite>",
	"lat": 24.29223421,
	"long": 45.47571313,
	"date_start": "01-06-2025 00:00",
	"date_end": "01-12-2025 16:00",
	"km_start": "228+850",
	"km_end": "228+900"
},
{
	"coords": "[24.03030014, 44.74890137]",
	"culoare": 0,
	"raza": 7,
	"categorie": 5.0,
	"name": "Circulatie ingreunata  DN67B",
	"Judet": "VL;",
	"UAT": "Măciuca;",
	"Localitati": "OVESELU (VL) -",
	"Km": "91+788 - 91+828",
	"Cauza": "Alunecare de teren cu afectare corp drum.",
	"Masuri de remediere": "Circulatia se desfasoara pe 1/2 cale , semnalizat cu indicatoare rutiere si restrictie viteza de 30 km/h .",
	"lat": 24.03030014,
	"long": 44.74890137,
	"date_start": "01-06-2025 00:00",
	"date_end": "01-12-2025 16:00",
	"km_start": "91+788",
	"km_end": "91+828"
},
{
	"coords": "[27.3930562, 46.20245385]",
	"culoare": 0,
	"raza": 7,
	"categorie": 5.0,
	"name": "Circulatie ingreunata  DN11A",
	"Judet": "BC;",
	"UAT": "Podu Turcului;",
	"Localitati": "CABESTI (BC) - CABESTI (BC)",
	"Km": "67+350 - 67+380",
	"Cauza": "Cedare terasament corp drum.",
	"Masuri de remediere": "Latime - 3m. Viteza - 30km/h.",
	"lat": 27.3930562,
	"long": 46.20245385,
	"date_start": "08-11-2024 09:38",
	"date_end": "31-12-2025 23:59",
	"km_start": "67+350",
	"km_end": "67+380"
},
{
	"coords": "[26.74674737, 45.90855167]",
	"culoare": 0,
	"raza": 7,
	"categorie": 5.0,
	"name": "Circulatie ingreunata  DN2D",
	"Judet": "VN;",
	"UAT": "Bârsești;",
	"Localitati": "BARSESTI (VN) - BARSESTI (VN)",
	"Km": "52+662 - 52+677",
	"Cauza": "Alunecare teren cu antrenare terasament corp drum.",
	"Masuri de remediere": "Circulatie ingreunata.",
	"lat": 26.74674737,
	"long": 45.90855167,
	"date_start": "08-11-2024 10:00",
	"date_end": "31-12-2025 23:59",
	"km_start": "52+662",
	"km_end": "52+677"
},
{
	"coords": "[23.98294253, 45.14278617]",
	"culoare": 0,
	"raza": 7,
	"categorie": 5.0,
	"name": "Circulatie ingreunata  DN67",
	"Judet": "VL;",
	"UAT": "Horezu;",
	"Localitati": "HOREZU (VL) -",
	"Km": "151+170 - 151+180",
	"Cauza": "Alunecare de teren .",
	"Masuri de remediere": "Circulatie ingreunata 1/2 cale si prin parcarea adiacenta. Zona este semnalizata corespunzator (alunecarea de teren este activa).",
	"lat": 23.98294253,
	"long": 45.14278617,
	"date_start": "01-06-2025 00:00",
	"date_end": "01-12-2025 16:00",
	"km_start": "151+170",
	"km_end": "151+180"
},
{
	"coords": "[23.63229942, 44.87820053]",
	"culoare": 0,
	"raza": 7,
	"categorie": 5.0,
	"name": "Circulatie ingreunata  DN67B",
	"Judet": "GJ;",
	"UAT": "Licurici;",
	"Localitati": "FRUMUSEI (GJ) -",
	"Km": "24+403",
	"Cauza": "Pod degradat.",
	"Masuri de remediere": "Circulatia se desfasoara pe 1/2 cale . Zona este semnalizata corespunzator .",
	"lat": 23.63229942,
	"long": 44.87820053,
	"date_start": "01-06-2025 00:00",
	"date_end": "31-12-2025 16:00"
},
{
	"coords": "[22.67205585, 45.02192819]",
	"culoare": 0,
	"raza": 7,
	"categorie": 5.0,
	"name": "Circulatie ingreunata  DN67D",
	"Judet": "MH;",
	"UAT": "Obîrșia-Cloșani;",
	"Localitati": "OBARSIA-CLOSANI (MH) - GODEANU (GODEANU) (MH)",
	"Km": "58+800",
	"Cauza": "Degradare terasament si parapet.",
	"Masuri de remediere": "Circulatia se desfasoara pe 1/2 cale . Zona este semnalizata corespunzator .",
	"lat": 22.67205585,
	"long": 45.02192819,
	"date_start": "31-07-2025 00:00",
	"date_end": "31-12-2025 16:00"
},
{
	"coords": "[25.99580569, 47.14375187]",
	"culoare": 0,
	"raza": 7,
	"categorie": 5.0,
	"name": "Circulatie ingreunata  DN15B",
	"Judet": "NT;",
	"UAT": "Poiana Teiului;",
	"Localitati": "PETRU VODA (NT) - PETRU VODA (NT)",
	"Km": "7+280",
	"Cauza": "Placa carosabila de beton a cedat intre grinzile principale ale podului.",
	"Masuri de remediere": "Circulatia este deschisa pe un fir alternativ si dirijat,pentru toate categoriile de autovehicule.",
	"lat": 25.99580569,
	"long": 47.14375187,
	"date_start": "01-03-2024 23:20",
	"date_end": "15-01-2026 11:00"
},
{
	"coords": "[21.73675427, 45.04825724]",
	"culoare": 0,
	"raza": 7,
	"categorie": 5.0,
	"name": "Circulatie ingreunata  DN57B",
	"Judet": "CS;",
	"UAT": "Oravița;",
	"Localitati": "ORAVITA (CS) - ORAVITA (CS)",
	"Km": "4+950",
	"Cauza": "In urma ploilor abundente, s-a produs o alunecare de teren.",
	"Masuri de remediere": "Circulatia rutiera este ingreunata pe 1/2 cale.",
	"lat": 21.73675427,
	"long": 45.04825724,
	"date_start": "31-05-2024 21:00",
	"date_end": "31-05-2026 12:00"
},
{
	"coords": "[22.70108613, 45.13828437]",
	"culoare": 0,
	"raza": 7,
	"categorie": 5.0,
	"name": "Circulatie ingreunata  DN66A",
	"Judet": "GJ;",
	"UAT": "Padeș;",
	"Localitati": "CERNA SAT (GJ) -",
	"Km": "93+050",
	"Cauza": "Drum rupt.",
	"Masuri de remediere": "Circulatia se desfasoara pe 1/2 cale. Zona este semnalizata corespunzator.",
	"lat": 22.70108613,
	"long": 45.13828437,
	"date_start": "01-02-2025 00:00",
	"date_end": "30-10-2025 16:00"
},
{
	"coords": "[22.69707279, 45.13721186]",
	"culoare": 0,
	"raza": 7,
	"categorie": 5.0,
	"name": "Circulatie ingreunata  DN66A",
	"Judet": "GJ;",
	"UAT": "Padeș;",
	"Localitati": "CERNA SAT (GJ) -",
	"Km": "93+800",
	"Cauza": "Drum rupt.",
	"Masuri de remediere": "Circulatia se defasoara pe 1/2 cale . Zona este semnalizata corespunzator .",
	"lat": 22.69707279,
	"long": 45.13721186,
	"date_start": "01-02-2025 00:00",
	"date_end": "30-10-2025 16:00"
},
{
	"coords": "[24.30310059, 44.66260147]",
	"culoare": 0,
	"raza": 7,
	"categorie": 5.0,
	"name": "Circulatie ingreunata  DN67B",
	"Judet": "OT;",
	"UAT": "Verguleasa;",
	"Localitati": "DRAGASANI (VL) - POGANU (OT)",
	"Km": "119+236",
	"Cauza": "Podul peste raul Olt nu prezinta siguranta pentru autovehiculele cu MTMA > 7,5 TO .",
	"Masuri de remediere": "Circulati a rutiera se desfasoara pe1/2 cale , dirijata prin semafoare. Ruta ocolitoare pentru autovehiculele cu MTMA > 7,5 TO - DN 64 - DJ 678C - DJ 678 - DN 67B.",
	"lat": 24.30310059,
	"long": 44.66260147,
	"date_start": "01-02-2025 00:00",
	"date_end": "30-10-2025 16:00"
},
{
	"coords": "[24.34175395, 45.2488953]",
	"culoare": 0,
	"raza": 7,
	"categorie": 5.0,
	"name": "Circulatie ingreunata  DN7CC",
	"Judet": "VL;",
	"UAT": "Călimănești;",
	"Localitati": "JIBLEA NOUA (VL) - PAUSA (VL)",
	"Km": "3+150",
	"Cauza": "Alunecare de teren",
	"Masuri de remediere": "Circulatia se desfasoara alternativ pe 1/2 cale cu restictionare pe sensul Sibiu - Rm. Valcea, dirijata cu semafoare si semnalizata cu balize, indicatoare rutiere si lampi cu iluminare intermitenta.",
	"lat": 24.34175395,
	"long": 45.2488953,
	"date_start": "01-06-2025 00:00",
	"date_end": "01-12-2025 16:00"
},
{
	"coords": "[23.73630222, 44.52582927]",
	"culoare": 0,
	"raza": 7,
	"categorie": 5.0,
	"name": "Circulatie ingreunata  DN6B",
	"Judet": "DJ;",
	"UAT": "Melinești;",
	"Localitati": "NEGOIESTI (DJ) -",
	"Km": "24+183",
	"Cauza": "Pod degradat.",
	"Masuri de remediere": "Circulatia rutiera se desfasoara ingreunat pe 1/2 cale, dirijata prin indicatoare rutiere, iar accesul autovehiculelor cu MTMA > 25 to este interzis.",
	"lat": 23.73630222,
	"long": 44.52582927,
	"date_start": "01-06-2025 00:00",
	"date_end": "01-12-2025 16:00"
},
{
	"coords": "[27.25085573, 46.17995095]",
	"culoare": 0,
	"raza": 7,
	"categorie": 5.0,
	"name": "Circulatie ingreunata  DN11A",
	"Judet": "VN;",
	"UAT": "Homocea;",
	"Localitati": "LESPEZI (VN) - LESPEZI (VN)",
	"Km": "52+025",
	"Cauza": "Ravenari terasament corp drum.",
	"Masuri de remediere": "Latime - 4m",
	"lat": 27.25085573,
	"long": 46.17995095,
	"date_start": "08-11-2024 09:28",
	"date_end": "31-12-2025 23:59"
},
{
	"coords": "[26.96820068, 45.96419907]",
	"culoare": 0,
	"raza": 7,
	"categorie": 5.0,
	"name": "Circulatie ingreunata  DN2L",
	"Judet": "VN;",
	"UAT": "Răcoasa;",
	"Localitati": "VARNITA (VN) - VARNITA (VN)",
	"Km": "27+750",
	"Cauza": "Pod de beton degradat.",
	"Masuri de remediere": "Masa - 30t. Viteza - 30km/h.",
	"lat": 26.96820068,
	"long": 45.96419907,
	"date_start": "08-11-2024 09:40",
	"date_end": "31-12-2025 23:59"
},
{
	"coords": "[26.94809914, 45.98350143]",
	"culoare": 0,
	"raza": 7,
	"categorie": 5.0,
	"name": "Circulatie ingreunata  DN2L",
	"Judet": "VN;",
	"UAT": "Răcoasa;",
	"Localitati": "VARNITA (VN) - VARNITA (VN)",
	"Km": "30+480",
	"Cauza": "Prabusire podet boltit.",
	"Masuri de remediere": "Latime - 3m. Viteza - 50km/h.",
	"lat": 26.94809914,
	"long": 45.98350143,
	"date_start": "08-11-2024 09:42",
	"date_end": "31-12-2025 23:59"
},
{
	"coords": "[26.80571603, 45.56267963]",
	"culoare": 0,
	"raza": 7,
	"categorie": 5.0,
	"name": "Circulatie ingreunata  DN2N",
	"Judet": "VN;",
	"UAT": "Chiojdeni;",
	"Localitati": "CHIOJDENI (VN) - CHIOJDENI (VN)",
	"Km": "45+190",
	"Cauza": "Surpare parte carosabila pod.",
	"Masuri de remediere": "Latime - 3,5m.",
	"lat": 26.80571603,
	"long": 45.56267963,
	"date_start": "08-11-2024 09:50",
	"date_end": "31-12-2025 23:59"
},
{
	"coords": "[26.76463522, 45.58503305]",
	"culoare": 0,
	"raza": 7,
	"categorie": 5.0,
	"name": "Circulatie ingreunata  DN2N",
	"Judet": "VN;",
	"UAT": "Jitia;",
	"Localitati": "JITIA (VN) - JITIA (VN)",
	"Km": "51+300",
	"Cauza": "Surpare parte carosabila.",
	"Masuri de remediere": "Latime - 3m. Viteza - 30km/h. Tonaj - 25t.",
	"lat": 26.76463522,
	"long": 45.58503305,
	"date_start": "08-11-2024 09:55",
	"date_end": "31-12-2025 23:59"
},
{
	"coords": "[26.75891053, 45.58641533]",
	"culoare": 0,
	"raza": 7,
	"categorie": 5.0,
	"name": "Circulatie ingreunata  DN2N",
	"Judet": "VN;",
	"UAT": "Jitia;",
	"Localitati": "JITIA (VN) - JITIA (VN)",
	"Km": "51+800",
	"Cauza": "Prabusire sfert con culee Cl",
	"Masuri de remediere": "Latime - 3m. Tonaj - 25t.",
	"lat": 26.75891053,
	"long": 45.58641533,
	"date_start": "08-11-2024 09:58",
	"date_end": "31-12-2025 23:59"
},
{
	"coords": "[26.85435599, 45.78229399]",
	"culoare": 0,
	"raza": 7,
	"categorie": 5.0,
	"name": "Circulatie ingreunata  DN2M",
	"Judet": "VN;",
	"UAT": "Reghiu;",
	"Localitati": "REGHIU (VN) - REGHIU (VN)",
	"Km": "30+853",
	"Cauza": "Spalarea umpluturii sfertului de con.",
	"Masuri de remediere": "Circulatie ingreunata.",
	"lat": 26.85435599,
	"long": 45.78229399,
	"date_start": "08-11-2024 10:04",
	"date_end": "31-12-2025 23:59"
},
{
	"coords": "[26.49516742, 46.95321658]",
	"culoare": 0,
	"raza": 7,
	"categorie": 5.0,
	"name": "Circulatie ingreunata  DN15D",
	"Judet": "NT;",
	"UAT": "Girov;",
	"Localitati": "GIROV (NT) - GIROV (NT)",
	"Km": "9+510",
	"Cauza": "Au inceput lucrarile la podul de pe DN 15D, Girov, judetul Neamt. Traficul se desfasoara, semaforizat, pe varianta provizorie, cu restrictie de tonaj de 30. In aceasta dimineata, a fost data in trafic varianta provizorie peste paraul Cracau, aferenta podului de pe DN 15D, km 9+510, Girov, judetul Ne...\n<cite>*Pentru descrierea completa consultati sectiunea drumuri.</cite>",
	"lat": 26.49516742,
	"long": 46.95321658,
	"date_start": "10-03-2025 10:03",
	"date_end": "30-11-2025 23:59"
},
{
	"coords": "[26.30410004, 45.41550064]",
	"culoare": 2,
	"raza": 7,
	"categorie": 6.0,
	"name": "Lucrari  DN10",
	"Judet": "BZ;",
	"UAT": "Nehoiu;",
	"Localitati": "NEHOIU (BZ) - NEHOIU (BZ)",
	"Km": "67+190",
	"Tip Lucrari": "Punerea in siguranta a traficului auto si pietonal pe tronsonul DN10, km 67+190, peste Nehoiu la Nehoiu, oras Nehoiu, jud. Buzau",
	"Variante de ocolire": "Circulatie pietonala - inchisa(stanga). Circulatie autoturisme - ingreunata\nIntre km 67+090 - km 67+280: restrictie de tonaj (MTMA<30 tone) si limitarea vitezei la 30 km/h\nDrum ingustat, circulatie pe o singura banda, prioritate sens Buzau - Brasov\nIntre km 67+127 - km 67+212: limitarea vit...\n<cite>*Pentru descrierea completa consultati sectiunea drumuri.</cite>",
	"lat": 26.30410004,
	"long": 45.41550064,
	"date_start": "14-03-2025 16:29",
	"date_end": "30-11-2025 17:00"
},
{
	"coords": "[22.25219454, 44.61607864]",
	"culoare": 0,
	"raza": 7,
	"categorie": 5.0,
	"name": "Circulatie ingreunata  DN57",
	"Judet": "MH;",
	"UAT": "Dubova;",
	"Localitati": "ESELNITA (MH) - DUBOVA (MH)",
	"Km": "25+811",
	"Cauza": "Tasare parte carosabila.",
	"Masuri de remediere": "Circulatia rutiera se desfasoara pe 1/2 cale, zona este semnalizata corespunzator.",
	"lat": 22.25219454,
	"long": 44.61607864,
	"date_start": "31-07-2025 00:00",
	"date_end": "31-10-2025 16:00"
},
{
	"coords": "[22.61688731, 45.04180384]",
	"culoare": 0,
	"raza": 7,
	"categorie": 5.0,
	"name": "Circulatie ingreunata  DN67D",
	"Judet": "MH;",
	"UAT": "Obîrșia-Cloșani;",
	"Localitati": "GODEANU (GODEANU) (MH) -",
	"Km": "70+790",
	"Cauza": "Zid de sprijin rupt.",
	"Masuri de remediere": "Circulatia rutiera se desfasoara pe 1/2 cale, semnalizata cu indicatoare rutiere.",
	"lat": 22.61688731,
	"long": 45.04180384,
	"date_start": "31-07-2025 00:00",
	"date_end": "31-12-2025 16:00"
},
{
	"coords": "[23.51961279, 47.65155309]",
	"culoare": 1,
	"raza": 7,
	"categorie": 4.0,
	"name": "Circulatie intrerupta  VO_BAIA_MARE(VOBM)",
	"Judet": "MM;",
	"UAT": "Baia Mare;",
	"Localitati": "BAIA MARE (MM) - BAIA MARE (MM)",
	"Km": "0+200",
	"Cauza": "Circulatie inchisa total pe o perioada nedeterminata pe E58(VOBM) la km 0+200 la trecerea peste raul Sasar. In urma averselor din ultima perioada structura piloniilor a fost afectata.",
	"Masuri de remediere si variante de ocolire": "Pe relatia Baia Mare - Sighet - Targu Lapus circulatie se desfasoara pe aceiasi ruta.\nVarianta de ocolire pentru Baia Mare- Satu Mare se va face prin oras, atat pentru autovehicule cu MTM<3.5t cat si pentru autovehicule cu MTM >3.5t respectiv pe Bulevardul Regele Mihai I (DN1C), Bulevardul Dece...\n<cite>*Pentru descrierea completa consultati sectiunea drumuri.</cite>",
	"lat": 23.51961279,
	"long": 47.65155309,
	"date_start": "07-07-2025 08:20",
	"date_end": "31-12-2025 23:59"
},
{
	"coords": "[23.54329123, 45.9907922]",
	"culoare": 1,
	"raza": 7,
	"categorie": 4.0,
	"name": "Circulatie intrerupta  A10",
	"Judet": "AB;",
	"UAT": "Sebeș;",
	"Km": "0+000",
	"Cauza": "Circulatia inchisa pe breteaua 2 , Nod Sebes , Autostrada A10, din cauza lucrarilor de consolidare pasaj PN02 peste Autostrada A1, peste calea ferata si peste breteaua 3.\nLucrari de drum:\n- consolidare culee S01\n-demolare placa de racordare\n-completare fundatie cu 2 coloane forate\nFor...\n<cite>*Pentru descrierea completa consultati sectiunea drumuri.</cite>",
	"Masuri de remediere si variante de ocolire": "Autostrada A1 - iesire Sebes Nord - Sens giratoriu 1 DN1 (directia Alba Iulia) - Sens giratoriu 2 DN1 - bretea 6 Nod Rutier Sebes - autostrada A10.",
	"lat": 23.54329123,
	"long": 45.9907922,
	"date_start": "21-07-2025 07:00",
	"date_end": "21-11-2025 18:00"
},
{
	"coords": "[23.72386889, 46.35234246]",
	"culoare": 2,
	"raza": 7,
	"categorie": 6.0,
	"name": "Lucrari  A10",
	"Judet": "AB;",
	"UAT": "Aiud;",
	"Localitati": "TURDA (CJ) - AIUD (AB)",
	"Km": "47+500",
	"Tip Lucrari": "Reparatie rost de dilatatie viaduc raul Mures .",
	"Variante de ocolire": "Lucrarile se desfasoara pe Calea 2, banda 1 si banda de urgenta blocate, se circula pe banda 2 cu restrictie de viteza .",
	"lat": 23.72386889,
	"long": 46.35234246,
	"date_start": "04-10-2025 12:10",
	"date_end": "21-10-2025 23:59"
},
{
	"coords": "[22.53266697, 45.92957302]",
	"culoare": 2,
	"raza": 7,
	"categorie": 6.0,
	"name": "Lucrari  A1",
	"Judet": "HD;",
	"UAT": "Gurasada;",
	"Localitati": "DOBRA (HD) - DOBRA (HD)",
	"Km": "399+500",
	"Tip Lucrari": "A1 km 399+500-Calea 1 Dobra - Lucrari - Inlocuire rosturi de dilatatie, se circula pe B2, iar BU si B1 sunt restrictionate, se estimeaza reluarea normala a circulatiei in data de 17.10.25, ora 16:00.",
	"lat": 22.53266697,
	"long": 45.92957302,
	"date_start": "07-10-2025 08:30",
	"date_end": "17-10-2025 16:00"
},
{
	"coords": "[22.53266697, 45.92957302]",
	"culoare": 2,
	"raza": 7,
	"categorie": 1.1,
	"name": "Lucrari de scurta durata  A1",
	"Judet": "HD;",
	"UAT": "Gurasada;",
	"Localitati": "DOBRA (HD) - DOBRA (HD)",
	"Km": "399+500",
	"Cauza": "Pe calea 2 se executa lucrari de inlocuiri rosturi de dilatatie.",
	"Masuri de remediere": "Se circula pe Banda 2.\nBanda 1 si Banda de urgenta sunt restrictionate.",
	"lat": 22.53266697,
	"long": 45.92957302,
	"date_start": "10-10-2025 15:00",
	"date_end": "22-10-2025 16:00"
},
{
	"coords": "[22.55320262, 45.93661546]",
	"culoare": 2,
	"raza": 7,
	"categorie": 1.1,
	"name": "Lucrari de scurta durata  A1",
	"Judet": "HD;",
	"UAT": "Gurasada;",
	"Localitati": "GURASADA (HD) - GURASADA (HD)",
	"Km": "397+700",
	"Cauza": "Pe calea 2 se vor executa lucrari de reparatii gropi cu mixtura stocabila.",
	"Masuri de remediere": "Banda 1 restrictionata. Se va circula pe banda 2.",
	"lat": 22.55320262,
	"long": 45.93661546,
	"date_start": "17-10-2025 09:00",
	"date_end": "17-10-2025 12:00"
},
{
	"coords": "[23.24008682, 45.88629456]",
	"culoare": 2,
	"raza": 7,
	"categorie": 1.1,
	"name": "Lucrari de scurta durata  A1",
	"Judet": "HD;",
	"UAT": "Geoagiu;",
	"Localitati": "GEOAGIU (HD) - GEOAGIU (HD)",
	"Km": "336+500",
	"Cauza": "Pe calea 2 se vor executa lucrari de reparatii gropi cu mixtura stocabila.",
	"Masuri de remediere": "Banda 1 restrictionata. Se va circula pe banda 2.",
	"lat": 23.24008682,
	"long": 45.88629456,
	"date_start": "17-10-2025 12:30",
	"date_end": "17-10-2025 15:30"
},
{
	"coords": "[23.11604776, 44.60212764]",
	"culoare": 1,
	"raza": 10,
	"categorie": 1.0,
	"name": "Eveniment rutier  DN6",
	"Judet": "MH;",
	"UAT": "Strehaia;",
	"Localitati": "CIOCHIUTA (MH) -",
	"Km": "296+890",
	"Cauza": "Accident rutier, o coliziune intre un microbuz si un autoturism. Partea carosabila, curata si uscata. Nu sunt victime. Cauza accidentului, eroare umana.",
	"Masuri de remediere": "Circulatia rutiera se desfasoara pe 1/2 cale. La fata locului se afla Politia, Salvarea, Pompierii si o echipa de interventie de la Drumuri.",
	"lat": 23.11604776,
	"long": 44.60212764,
	"date_start": "17-10-2025 07:15",
	"date_end": "17-10-2025 10:00"
}
]