[
    {
        "id": "141",
        "name": "Centru-3",
        "citycode": "CJ",
        "city": "Cluj Napoca",
        "type": "3",
        "status": "true",
        "main": false,
        "lat": "46.771657",
        "long": "23.583675",
        "dev": [
            {
                "eui": "02090209",
                "date": "2025-09-08 06:00",
                "now": "2025-09-08 06:00",
                "pm1": 14.925,
                "pm25": 21.616666666667,
                "pm10": 25.95,
                "no2": 0,
                "so2": 0,
                "co": 0,
                "ica_pm1": 0,
                "ica_pm25": 54.041666666667,
                "ica_pm10": 43.25,
                "ica_no2": 0,
                "ica_so2": 0,
                "ica_co": 0,
                "ica": 54.041666666667,
                "max_value": 21.616666666667
            }
        ],
        "devices": [
            {
                "eui": "02090209",
                "date": "2025-09-08 06:00",
                "now": "2025-09-08 06:00",
                "pm1": 14.925,
                "pm25": 21.616666666667,
                "pm10": 25.95,
                "no2": 0,
                "so2": 0,
                "co": 0,
                "ica_pm1": 0,
                "ica_pm25": 54.041666666667,
                "ica_pm10": 43.25,
                "ica_no2": 0,
                "ica_so2": 0,
                "ica_co": 0,
                "ica": 54.041666666667,
                "max_value": 21.616666666667
            }
        ],
        "cluster_ica_data": [],
        "highest": {
            "eui": "02090209",
            "date": "2025-09-08 06:00",
            "now": "2025-09-08 06:00",
            "pm1": 14.925,
            "pm25": 21.616666666667,
            "pm10": 25.95,
            "no2": 0,
            "so2": 0,
            "co": 0,
            "ica_pm1": 0,
            "ica_pm25": 54.041666666667,
            "ica_pm10": 43.25,
            "ica_no2": 0,
            "ica_so2": 0,
            "ica_co": 0,
            "ica": 54.041666666667,
            "max_value": 21.616666666667
        },
        "highest_ica": 54.041666666667,
        "ica": {
            "number": 54.041666666667,
            "color": "yellow"
        },
        "max_value": 21.616666666667,
        "lastReadingTime": "2025-09-08 06:00"
    },
    {
        "id": "139",
        "name": "Someșeni-1",
        "citycode": "CJ",
        "city": "Cluj Napoca",
        "type": "3",
        "status": "true",
        "main": false,
        "lat": "46.781348",
        "long": "23.664296",
        "dev": [
            {
                "eui": "02090479",
                "date": "2025-09-08 06:00",
                "now": "2025-09-08 06:00",
                "pm1": 20.516666666667,
                "pm25": 28.933333333333,
                "pm10": 34.3,
                "no2": 0,
                "so2": 0,
                "co": 0,
                "ica_pm1": 0,
                "ica_pm25": 72.333333333333,
                "ica_pm10": 55.375,
                "ica_no2": 0,
                "ica_so2": 0,
                "ica_co": 0,
                "ica": 72.333333333333,
                "max_value": 28.933333333333
            }
        ],
        "devices": [
            {
                "eui": "02090479",
                "date": "2025-09-08 06:00",
                "now": "2025-09-08 06:00",
                "pm1": 20.516666666667,
                "pm25": 28.933333333333,
                "pm10": 34.3,
                "no2": 0,
                "so2": 0,
                "co": 0,
                "ica_pm1": 0,
                "ica_pm25": 72.333333333333,
                "ica_pm10": 55.375,
                "ica_no2": 0,
                "ica_so2": 0,
                "ica_co": 0,
                "ica": 72.333333333333,
                "max_value": 28.933333333333
            }
        ],
        "cluster_ica_data": [],
        "highest": {
            "eui": "02090479",
            "date": "2025-09-08 06:00",
            "now": "2025-09-08 06:00",
            "pm1": 20.516666666667,
            "pm25": 28.933333333333,
            "pm10": 34.3,
            "no2": 0,
            "so2": 0,
            "co": 0,
            "ica_pm1": 0,
            "ica_pm25": 72.333333333333,
            "ica_pm10": 55.375,
            "ica_no2": 0,
            "ica_so2": 0,
            "ica_co": 0,
            "ica": 72.333333333333,
            "max_value": 28.933333333333
        },
        "highest_ica": 72.333333333333,
        "ica": {
            "number": 72.333333333333,
            "color": "yellow"
        },
        "max_value": 28.933333333333,
        "lastReadingTime": "2025-09-08 06:00"
    },
    {
        "id": "139",
        "name": "Cluj Napoca",
        "citycode": "CJ",
        "city": "Cluj Napoca",
        "type": "3",
        "status": "true",
        "main": true,
        "lat": "46.781348",
        "long": "23.664296",
        "dev": [
            {
                "eui": "02090479",
                "date": "2025-09-08 06:00",
                "now": "2025-09-08 06:00",
                "pm1": 20.516666666667,
                "pm25": 28.933333333333,
                "pm10": 34.3,
                "no2": 0,
                "so2": 0,
                "co": 0,
                "ica_pm1": 0,
                "ica_pm25": 72.333333333333,
                "ica_pm10": 55.375,
                "ica_no2": 0,
                "ica_so2": 0,
                "ica_co": 0,
                "ica": 72.333333333333,
                "max_value": 28.933333333333
            }
        ],
        "devices": [
            {
                "eui": "02090479",
                "date": "2025-09-08 06:00",
                "now": "2025-09-08 06:00",
                "pm1": 20.516666666667,
                "pm25": 28.933333333333,
                "pm10": 34.3,
                "no2": 0,
                "so2": 0,
                "co": 0,
                "ica_pm1": 0,
                "ica_pm25": 72.333333333333,
                "ica_pm10": 55.375,
                "ica_no2": 0,
                "ica_so2": 0,
                "ica_co": 0,
                "ica": 72.333333333333,
                "max_value": 28.933333333333
            }
        ],
        "cluster_ica_data": [],
        "highest": {
            "eui": "02090479",
            "date": "2025-09-08 06:00",
            "now": "2025-09-08 06:00",
            "pm1": 20.516666666667,
            "pm25": 28.933333333333,
            "pm10": 34.3,
            "no2": 0,
            "so2": 0,
            "co": 0,
            "ica_pm1": 0,
            "ica_pm25": 72.333333333333,
            "ica_pm10": 55.375,
            "ica_no2": 0,
            "ica_so2": 0,
            "ica_co": 0,
            "ica": 72.333333333333,
            "max_value": 28.933333333333
        },
        "highest_ica": 72.333333333333,
        "ica": {
            "number": 72.333333333333,
            "color": "yellow"
        },
        "max_value": 28.933333333333,
        "lastReadingTime": "2025-09-08 06:00"
    }
]