{"NUMAR LUCRARE":"58895","JUDE\u021a":"DAMBOVITA","ADRESA":"Loc: VISINESTI, Sat: VISINESTI","DATA \u00ceNCEPERE":"20\/07\/2024 22:00","DATA FINALIZARE":"","zona":"MN"}
{"NUMAR LUCRARE":"58894","JUDE\u021a":"PRAHOVA","ADRESA":"Loc: VALCANESTI, Sat: TRESTIOARA","DATA \u00ceNCEPERE":"20\/07\/2024 21:15","DATA FINALIZARE":"","zona":"MN"}
{"NUMAR LUCRARE":"58860","JUDE\u021a":"DAMBOVITA","ADRESA":"Loc: POIANA, Sat: POIANA","DATA \u00ceNCEPERE":"19\/07\/2024 08:14","DATA FINALIZARE":"","zona":"MN"}
{"NUMAR LUCRARE":"58801","JUDE\u021a":"DAMBOVITA","ADRESA":"Loc: MATASARU, Sat: TETCOIU, Str.: TETCOIU","DATA \u00ceNCEPERE":"19\/07\/2024 06:41","DATA FINALIZARE":"","zona":"MN"}
{"NUMAR LUCRARE":"58630","JUDE\u021a":"DAMBOVITA","ADRESA":"Loc: SELARU, Sat: FIERBINTI","DATA \u00ceNCEPERE":"16\/07\/2024 19:20","DATA FINALIZARE":"","zona":"MN"}
