{
  "poze": [],
  "hasFinishedTransport": false,
  "codAviz": "DA26010008002211794003262009",
  "nrIdentificare": "HR82UEP",
  "nrApv": null,
  "provenienta": "DEP REPUBLICII ",
  "tipAviz": 2,
  "numeTipAviz": "Depozit",
  "volum": {
    "idAviz": 45137676,
    "volumSpecie": [
      {
        "numeSpecie": "RĂȘINOASE",
        "volumSortiment": [
          {
            "numeSortiment": "Rumeguș",
            "volum": 22.5
          }
        ],
        "volum": 22.5
      }
    ],
    "total": 22.5
  },
  "emitent": {
    "denumire": "Ampfen-lemn S.R.L.",
    "cui": "21917384"
  },
  "transportator": {
    "identificator": "HR82UEP",
    "denumire": "Ampfen-lemn S.R.L.",
    "cui": "21917384",
    "tip": "SUMAL",
    "nonSumal": false
  },
  "beneficiar": {
    "tip": "JURIDICA"
  },
  "destinatar": {
    "tip": "JURIDICA"
  },
  "valabilitate": {
    "emitere": 1774548564429,
    "finalizare": 1774613364429
  },
  "tipMarfa": null,
  "angajat": null,
  "remorca": null,
  "identificatorContainer": "",
  "marfa": {
    "grupeSpecii": "RĂȘINOASE",
    "specii": "MOLID ",
    "sortimente": "Rumeguș",
    "total": 22.5
  }
}